phasescreen/__init__.py
phasescreen/_elt_pupil_utils.py
phasescreen/base.py
phasescreen/disk_pupil.py
phasescreen/elt_pupil.py
phasescreen/phasescreen.py
phasescreen/rectangular_pupil.py
phasescreen/utils.py
phasescreen-0.1.6.dist-info/METADATA
phasescreen-0.1.6.dist-info/WHEEL
phasescreen-0.1.6.dist-info/RECORD
