Metadata-Version: 2.1
Name: phasescreen
Version: 0.1.6
Summary: 
Author: Sylvain Guieu
Author-email: sylvain.guieu@gmail.com
Requires-Python: >=3.8,<4.0
Classifier: Programming Language :: Python :: 3
Classifier: Programming Language :: Python :: 3.8
Classifier: Programming Language :: Python :: 3.9
Classifier: Programming Language :: Python :: 3.10
Classifier: Programming Language :: Python :: 3.11
Requires-Dist: zernpol (>=0.1.5,<0.2.0)
